agent0_sdk/__init__.py
agent0_sdk/core/agent.py
agent0_sdk/core/contracts.py
agent0_sdk/core/endpoint_crawler.py
agent0_sdk/core/feedback_manager.py
agent0_sdk/core/greenfield_gateway_storage.py
agent0_sdk/core/greenfield_storage.py
agent0_sdk/core/indexer.py
agent0_sdk/core/ipfs_client.py
agent0_sdk/core/ipfs_storage.py
agent0_sdk/core/models.py
agent0_sdk/core/oasf_validator.py
agent0_sdk/core/sdk.py
agent0_sdk/core/storage_factory.py
agent0_sdk/core/storage_interfaces.py
agent0_sdk/core/subgraph_client.py
agent0_sdk/core/web3_client.py
hubble_agent0-0.33.0.dist-info/licenses/LICENSE
onchain/node_modules/@ethersproject/json-wallets/node_modules/aes-js/generate-tests.py
onchain/node_modules/@ethersproject/json-wallets/node_modules/aes-js/run-readme.py
scripts/bsc_testnet_agent_subgraph_check.py
tests/__init__.py
tests/config.py
tests/conftest.py
tests/run_greenfield_e2e_improved.py
tests/test_config_fix.py
tests/test_feedback.py
tests/test_greenfield_e2e.py
tests/test_models.py
tests/test_multi_chain.py
tests/test_oasf_management.py
tests/test_phase3_bnb_feedback.py
tests/test_phase3_bnb_integration.py
tests/test_phase3_bnb_query.py
tests/test_phase3_bnb_registration.py
tests/test_phase3_bnb_simple.py
tests/test_real_public_servers.py
tests/test_registration.py
tests/test_registrationIpfs.py
tests/test_sdk.py
tests/test_sdk_content_storage.py
tests/test_search.py
tests/test_transfer.py
hubble_agent0-0.33.0.dist-info/METADATA
hubble_agent0-0.33.0.dist-info/WHEEL
hubble_agent0-0.33.0.dist-info/top_level.txt
hubble_agent0-0.33.0.dist-info/RECORD
