Metadata-Version: 2.4
Name: hubble-agent0
Version: 0.33.0
Summary: Python SDK for agent portability, discovery and trust based on ERC-8004 (Hubble fork with enhanced features)
Author-email: Hubble Vision Team <dev@hubblevision.io>, Marco De Rossi <marco.derossi@consensys.net>
License: MIT License
Project-URL: Homepage, https://github.com/HubbleVision/agent0-py
Project-URL: Repository, https://github.com/HubbleVision/agent0-py
Project-URL: Documentation, https://github.com/HubbleVision/agent0-py#readme
Project-URL: Source Code, https://github.com/HubbleVision/agent0-py
Project-URL: Original Project, https://github.com/agent0lab/agent0-py
Classifier: Development Status :: 3 - Alpha
Classifier: Intended Audience :: Developers
Classifier: License :: OSI Approved :: MIT License
Classifier: Programming Language :: Python :: 3
Classifier: Programming Language :: Python :: 3.8
Classifier: Programming Language :: Python :: 3.9
Classifier: Programming Language :: Python :: 3.10
Classifier: Programming Language :: Python :: 3.11
Classifier: Programming Language :: Python :: 3.12
Requires-Python: >=3.8
License-File: LICENSE
Requires-Dist: web3>=6.0.0
Requires-Dist: eth-account>=0.8.0
Requires-Dist: eth-utils>=2.0.0
Requires-Dist: requests>=2.28.0
Requires-Dist: pydantic>=2.0.0
Requires-Dist: ipfshttpclient>=0.8.0a2
Requires-Dist: aiohttp>=3.8.0
Requires-Dist: asyncio-throttle>=1.0.0
Requires-Dist: python-dotenv>=1.0.0
Requires-Dist: typing-extensions>=4.0.0
Provides-Extra: indexer
Requires-Dist: sentence-transformers>=2.2.0; extra == "indexer"
Provides-Extra: dev
Requires-Dist: pytest>=7.0.0; extra == "dev"
Requires-Dist: pytest-asyncio>=0.21.0; extra == "dev"
Requires-Dist: pytest-cov>=4.0.0; extra == "dev"
Requires-Dist: black>=22.0.0; extra == "dev"
Requires-Dist: isort>=5.10.0; extra == "dev"
Requires-Dist: mypy>=1.0.0; extra == "dev"
Requires-Dist: flake8>=5.0.0; extra == "dev"
Provides-Extra: test
Requires-Dist: pytest>=7.0.0; extra == "test"
Requires-Dist: pytest-asyncio>=0.21.0; extra == "test"
Requires-Dist: pytest-cov>=4.0.0; extra == "test"
Requires-Dist: pytest-mock>=3.10.0; extra == "test"
Dynamic: license-file
